{
  "Url": "https://www.baidu.com",
  "imgUrl": "../../../static/img/logo.png",
  "imgAlt": "顺丰速运",
  "NarDate": [
    {
      "ul": {
        "name": "首 页",
        "url": "https://www.baidu.com"
      },
      "li": []
    },
    {
      "ul": {
        "name": "寄大件",
        "url": "####"
      },
      "li": [
        {
          "name": "自助寄件",
          "url": "####"
        },
        {
          "name": "服务查询",
          "url": "####"
        },
        {
          "name": "月结客户服务",
          "url": "####"
        }
      ]
    },
    {
      "ul": {
        "name": "产品介绍",
        "url": "####"
      },
      "li": [
        {
          "name": "重货包裹",
          "url": "####"
        },
        {
          "name": "标准零担",
          "url": "####"
        },
        {
          "name": "大票直送",
          "url": "####"
        },
        {
          "name": "整车直达",
          "url": "####"
        }
      ]
    },
    {
      "ul": {
        "name": "增值服务",
        "url": "####"
      },
      "li": [
        {
          "name": "报价运输",
          "url": "####"
        },
        {
          "name": "代收货款",
          "url": "####"
        }
      ]
    },
    {
      "ul": {
        "name": "企业服务",
        "url": "####"
      },
      "li": [
        {
          "name": "SF开放平台",
          "url": "####"
        }
      ]
    },
    {
      "ul": {
        "name": "关于我们",
        "url": "####"
      },
      "li": []
    }
  ]
}
